httptools-0.6.3.dist-info/top_level.txt
httptools-0.6.3.dist-info/RECORD
httptools-0.6.3.dist-info/LICENSE
httptools-0.6.3.dist-info/METADATA
httptools-0.6.3.dist-info/WHEEL
httptools/__init__.py
httptools/_version.py
httptools/parser/errors.py
httptools/parser/parser.cpython-310-x86_64-linux-gnu.so
httptools/parser/__init__.py
httptools/parser/url_parser.cpython-310-x86_64-linux-gnu.so
