Metadata-Version: 2.1
Name: httptools
Version: 0.6.3
Summary: A collection of framework independent HTTP protocol utils.
Home-page: https://github.com/MagicStack/httptools
Author: Yury Selivanov
Author-email: yury@magic.io
License: MIT
Platform: macOS
Platform: POSIX
Platform: Windows
Classifier: License :: OSI Approved :: MIT License
Classifier: Intended Audience :: Developers
Classifier: Programming Language :: Python :: 3
Classifier: Operating System :: POSIX
Classifier: Operating System :: MacOS :: MacOS X
Classifier: Environment :: Web Environment
Classifier: Development Status :: 5 - Production/Stable
Requires-Python: >=3.8.0
License-File: LICENSE
Provides-Extra: test
Requires-Dist: Cython>=0.29.24; extra == "test"
